inferno/__init__.py
inferno/__main__.py
inferno/cli.py
inferno/main.py
inferno/config/__init__.py
inferno/config/server_config.py
inferno/memory/__init__.py
inferno/memory/memory_manager.py
inferno/models/__init__.py
inferno/models/converter.py
inferno/models/loader.py
inferno/models/registry.py
inferno/server/__init__.py
inferno/server/api.py
inferno/server/generation.py
inferno/server/routes.py
inferno/server/task_queue.py
inferno/tools/__init__.py
inferno/tools/convert_model.py
inferno/utils/__init__.py
inferno/utils/device.py
inferno/utils/logger.py
HelpingAI_inferno-0.1.3.dist-info/LICENSE
HelpingAI_inferno-0.1.3.dist-info/METADATA
HelpingAI_inferno-0.1.3.dist-info/WHEEL
HelpingAI_inferno-0.1.3.dist-info/entry_points.txt
HelpingAI_inferno-0.1.3.dist-info/top_level.txt
HelpingAI_inferno-0.1.3.dist-info/RECORD
