Metadata-Version: 2.1
Name: HelpingAI-inferno
Version: 0.1.3
Summary: A professional, production-ready inference server for running any AI model with universal model compatibility and multi-hardware support
Home-page: https://github.com/HelpingAI/inferno
Author: HelpingAI
Author-email: info@helpingai.co
Classifier: Development Status :: 4 - Beta
Classifier: Intended Audience :: Developers
Classifier: License :: OSI Approved :: MIT License
Classifier: Programming Language :: Python :: 3
Classifier: Programming Language :: Python :: 3.8
Classifier: Programming Language :: Python :: 3.9
Classifier: Programming Language :: Python :: 3.10
Requires-Python: >=3.8
License-File: LICENSE
Requires-Dist: torch>=2.0.0
Requires-Dist: transformers>=4.30.0
Requires-Dist: fastapi>=0.95.0
Requires-Dist: uvicorn>=0.22.0
Requires-Dist: pydantic>=1.10.0
Requires-Dist: requests>=2.28.0
Requires-Dist: tqdm>=4.64.0
Requires-Dist: py-cpuinfo>=9.0.0
Requires-Dist: bitsandbytes>=0.40.0
Requires-Dist: psutil>=5.9.0
Requires-Dist: huggingface-hub>=0.16.0
Requires-Dist: rich>=10.0.0
Requires-Dist: evaluate==0.3.0
Requires-Dist: accelerator>=0.20.0
Provides-Extra: converter
Requires-Dist: safetensors>=0.3.1; extra == "converter"
Requires-Dist: flax>=0.7.0; extra == "converter"
Provides-Extra: gguf
Requires-Dist: llama-cpp-python; extra == "gguf"
Requires-Dist: cmake; extra == "gguf"
Requires-Dist: ninja; extra == "gguf"
Provides-Extra: tpu
Requires-Dist: jax>=0.4.13; extra == "tpu"
Requires-Dist: jaxlib>=0.4.13; extra == "tpu"
Requires-Dist: flax>=0.7.0; extra == "tpu"
Requires-Dist: safetensors>=0.3.1; extra == "tpu"
Requires-Dist: torch-xla; extra == "tpu"
